{
  "status": "live",
  "asset": "MGC + MNQ + SIL",
  "account_mode": "combine",
  "started_at": "2026-02-26T07:52:29.280884+00:00",
  "updated_at": "2026-02-26T10:04:38.833063+00:00",
  "windows": [
    "[MGC] 23:00-23:30 CC=0.8",
    "[MGC] 01:00-01:30 CC=4.7",
    "[MGC] 02:00-02:30 CC=1.2",
    "[MGC] 00:00-00:30 CC=2.7",
    "[MGC] 14:00-14:30 CC=1.0",
    "[MNQ] 17:00-17:30 CC=6.6",
    "[MNQ] 21:00-21:30 CC=1.3",
    "[MNQ] 16:00-16:30 CC=4.6",
    "[MNQ] 20:30-21:00 CC=9.6",
    "[MNQ] 00:30-01:00 CC=2.3"
  ],
  "balance": 52075.92,
  "start_balance": 52075.92,
  "pnl": 0.0,
  "pnl_pct": 0.0,
  "trades": 0,
  "wins": 0,
  "losses": 0,
  "win_rate": 0,
  "open_orders": 0,
  "open_positions": 0,
  "last_signal": "",
  "cloud_color": "green",
  "ema_diff": 0.4674,
  "terminal": [
    "[09:59:01] [SIL] 09:58 \ud83d\udfe2 C=88.03 EMA=+0.0284",
    "[09:59:01] [MGC] 09:58 \ud83d\udfe2 C=5203.00 EMA=+1.3842",
    "[09:59:01] [MNQ] 09:58 \ud83d\udd34 C=25381.00 EMA=-3.2462",
    "[09:59:01] [MGC] 09:58 \ud83d\udfe2 C=5203.00 EMA=+0.9766",
    "[09:59:01] [MGC] 09:58 \ud83d\udfe2 C=5203.00 EMA=+0.7181",
    "[09:59:01] [MGC] 09:58 \ud83d\udfe2 C=5203.00 EMA=+0.5505",
    "[09:59:01] [MNQ] 09:58 \ud83d\udd34 C=25380.75 EMA=-3.1614",
    "[09:59:39] \ud83d\udcca [MGC] \ud83d\udfe2 EMA=+0.55 | [MNQ] \ud83d\udd34 EMA=-3.16 | [SIL] \ud83d\udfe2 EMA=+0.03",
    "[10:00:01] [MGC] 09:59 \ud83d\udfe2 C=5202.70 EMA=+0.3470",
    "[10:00:01] [SIL] 09:59 \ud83d\udd34\u26a1 C=88.00 EMA=-0.0059",
    "[10:00:01] [SIL] \u26a1 Cloud Change ignoriert: Zeit: 09:59 UTC",
    "[10:00:01] [MNQ] 09:59 \ud83d\udd34 C=25378.00 EMA=-3.8329",
    "[10:00:40] \ud83d\udcca [MGC] \ud83d\udfe2 EMA=+0.35 | [MNQ] \ud83d\udd34 EMA=-3.83 | [SIL] \ud83d\udd34 EMA=-0.01",
    "[10:01:01] [MGC] 10:00 \ud83d\udfe2 C=5202.80 EMA=+0.2539",
    "[10:01:01] [SIL] 10:00 \ud83d\udd34 C=88.00 EMA=-0.0212",
    "[10:01:01] [MNQ] 10:00 \ud83d\udd34 C=25380.25 EMA=-3.3658",
    "[10:01:40] \ud83d\udcca [MGC] \ud83d\udfe2 EMA=+0.25 | [MNQ] \ud83d\udd34 EMA=-3.37 | [SIL] \ud83d\udd34 EMA=-0.02",
    "[10:02:01] [MGC] 10:01 \ud83d\udfe2 C=5203.00 EMA=+0.2546",
    "[10:02:01] [MNQ] 10:01 \ud83d\udd34 C=25381.75 EMA=-2.5268",
    "[10:02:01] [SIL] 10:01 \ud83d\udd34 C=88.02 EMA=-0.0242",
    "[10:02:01] [MGC] 10:01 \ud83d\udfe2 C=5202.90 EMA=+0.2148",
    "[10:02:41] \ud83d\udcca [MGC] \ud83d\udfe2 EMA=+0.21 | [MNQ] \ud83d\udd34 EMA=-2.53 | [SIL] \ud83d\udd34 EMA=-0.02",
    "[10:03:01] [MNQ] 10:02 \ud83d\udd34 C=25379.00 EMA=-2.8132",
    "[10:03:01] [MGC] 10:02 \ud83d\udd34\u26a1 C=5202.10 EMA=-0.0588",
    "[10:03:01] [MGC] \u26a1 Cloud Change ignoriert: Zeit: 10:02 UTC",
    "[10:03:01] [SIL] 10:02 \ud83d\udd34 C=88.04 EMA=-0.0188",
    "[10:03:01] [MGC] 10:02 \ud83d\udd34 C=5202.40 EMA=-0.1137",
    "[10:03:01] [MGC] 10:02 \ud83d\udd34 C=5202.60 EMA=-0.0782",
    "[10:03:01] [SIL] 10:02 \ud83d\udd34 C=88.06 EMA=-0.0090",
    "[10:03:01] [MNQ] 10:02 \ud83d\udd34 C=25379.50 EMA=-2.7091",
    "[10:03:01] [SIL] 10:02 \ud83d\udd34 C=88.07 EMA=-0.0003",
    "[10:03:01] [MGC] 10:02 \ud83d\udfe2\u26a1 C=5203.00 EMA=+0.0660",
    "[10:03:01] [MGC] \u26a1 Cloud Change ignoriert: Zeit: 10:02 UTC",
    "[10:03:01] [MNQ] 10:02 \ud83d\udd34 C=25379.25 EMA=-2.6256",
    "[10:03:41] \ud83d\udcca [MGC] \ud83d\udfe2 EMA=+0.07 | [MNQ] \ud83d\udd34 EMA=-2.63 | [SIL] \ud83d\udd34 EMA=-0.00",
    "[10:04:01] [MNQ] 10:03 \ud83d\udd34 C=25381.25 EMA=-1.8707",
    "[10:04:01] [MGC] 10:03 \ud83d\udfe2 C=5203.30 EMA=+0.2332",
    "[10:04:01] [SIL] 10:03 \ud83d\udfe2\u26a1 C=88.08 EMA=+0.0090",
    "[10:04:01] [SIL] \u26a1 Cloud Change ignoriert: Zeit: 10:03 UTC",
    "[10:04:01] [MGC] 10:03 \ud83d\udfe2 C=5203.80 EMA=+0.4674"
  ]
}