{
  "status": "live",
  "asset": "MGC + MNQ",
  "account_mode": "combine",
  "started_at": "2026-03-04T17:05:00.010618+00:00",
  "updated_at": "2026-03-05T09:53:39.515608+00:00",
  "windows": [
    "[MGC] 01:00-01:30 CC=3.0",
    "[MGC] 23:00-23:30 CC=0.8",
    "[MGC] 02:00-02:30 CC=1.2",
    "[MGC] 10:30-11:00 CC=2.9",
    "[MGC] 12:00-12:30 CC=3.4",
    "[MNQ] 17:00-17:30 CC=6.7",
    "[MNQ] 20:30-21:00 CC=9.7",
    "[MNQ] 16:00-16:30 CC=4.9",
    "[MNQ] 23:00-23:30 CC=6.2",
    "[MNQ] 05:00-05:30 CC=4.2"
  ],
  "balance": 49724.38,
  "start_balance": 50385.82,
  "pnl": -661.4400000000023,
  "pnl_pct": -1.3127502936342057,
  "trades": 3,
  "wins": 0,
  "losses": 2,
  "win_rate": 0.0,
  "open_orders": 0,
  "open_positions": 0,
  "last_signal": "",
  "cloud_color": "red",
  "ema_diff": -1.1065,
  "terminal": [
    "[09:40:00] [MGC] 09:39 \ud83d\udd34 C=5166.90 EMA=-5.3611",
    "[09:40:38] \ud83d\udcca [MGC] \ud83d\udd34 EMA=-5.36 | [MNQ] \ud83d\udd34 EMA=-19.68",
    "[09:41:00] [MNQ] 09:40 \ud83d\udd34 C=25091.50 EMA=-23.9967",
    "[09:41:00] [MGC] 09:40 \ud83d\udd34 C=5171.00 EMA=-5.2300",
    "[09:41:38] \ud83d\udcca [MGC] \ud83d\udd34 EMA=-5.23 | [MNQ] \ud83d\udd34 EMA=-24.00",
    "[09:42:00] [MNQ] 09:41 \ud83d\udd34 C=25100.75 EMA=-22.6067",
    "[09:42:01] [MGC] 09:41 \ud83d\udd34 C=5173.90 EMA=-4.0758",
    "[09:42:39] \ud83d\udcca [MGC] \ud83d\udd34 EMA=-4.08 | [MNQ] \ud83d\udd34 EMA=-22.61",
    "[09:43:00] [MNQ] 09:42 \ud83d\udd34 C=25110.25 EMA=-18.0956",
    "[09:43:00] [MGC] 09:42 \ud83d\udd34 C=5176.60 EMA=-2.4711",
    "[09:43:39] \ud83d\udcca [MGC] \ud83d\udd34 EMA=-2.47 | [MNQ] \ud83d\udd34 EMA=-18.10",
    "[09:44:00] [MGC] 09:43 \ud83d\udd34 C=5173.20 EMA=-2.5420",
    "[09:44:00] [MNQ] 09:43 \ud83d\udd34 C=25096.75 EMA=-19.0717",
    "[09:44:39] \ud83d\udcca [MGC] \ud83d\udd34 EMA=-2.54 | [MNQ] \ud83d\udd34 EMA=-19.07",
    "[09:45:00] [MGC] 09:44 \ud83d\udd34 C=5173.10 EMA=-2.5141",
    "[09:45:00] [MNQ] 09:44 \ud83d\udd34 C=25092.25 EMA=-20.2465",
    "[09:45:40] \ud83d\udcca [MGC] \ud83d\udd34 EMA=-2.51 | [MNQ] \ud83d\udd34 EMA=-20.25",
    "[09:46:00] [MNQ] 09:45 \ud83d\udd34 C=25091.75 EMA=-20.2653",
    "[09:46:00] [MGC] 09:45 \ud83d\udd34 C=5169.30 EMA=-3.5613",
    "[09:46:40] \ud83d\udcca [MGC] \ud83d\udd34 EMA=-3.56 | [MNQ] \ud83d\udd34 EMA=-20.27",
    "[09:47:00] [MNQ] 09:46 \ud83d\udd34 C=25105.75 EMA=-15.2368",
    "[09:47:00] [MGC] 09:46 \ud83d\udd34 C=5172.00 EMA=-3.1713",
    "[09:47:40] \ud83d\udcca [MGC] \ud83d\udd34 EMA=-3.17 | [MNQ] \ud83d\udd34 EMA=-15.24",
    "[09:48:00] [MNQ] 09:47 \ud83d\udd34 C=25106.50 EMA=-11.6981",
    "[09:48:00] [MGC] 09:47 \ud83d\udd34 C=5171.20 EMA=-3.0825",
    "[09:48:40] \ud83d\udcca [MGC] \ud83d\udd34 EMA=-3.08 | [MNQ] \ud83d\udd34 EMA=-11.70",
    "[09:49:00] [MNQ] 09:48 \ud83d\udd34 C=25103.25 EMA=-10.3219",
    "[09:49:00] [MGC] 09:48 \ud83d\udd34 C=5172.10 EMA=-2.6426",
    "[09:49:40] \ud83d\udcca [MGC] \ud83d\udd34 EMA=-2.64 | [MNQ] \ud83d\udd34 EMA=-10.32",
    "[09:50:00] [MNQ] 09:49 \ud83d\udd34 C=25111.00 EMA=-6.8197",
    "[09:50:00] [MGC] 09:49 \ud83d\udd34 C=5175.40 EMA=-1.2975",
    "[09:50:41] \ud83d\udcca [MGC] \ud83d\udd34 EMA=-1.30 | [MNQ] \ud83d\udd34 EMA=-6.82",
    "[09:51:00] [MNQ] 09:50 \ud83d\udd34 C=25116.00 EMA=-3.1349",
    "[09:51:01] [MGC] 09:50 \ud83d\udd34 C=5175.30 EMA=-0.5483",
    "[09:51:41] \ud83d\udcca [MGC] \ud83d\udd34 EMA=-0.55 | [MNQ] \ud83d\udd34 EMA=-3.13",
    "[09:52:00] [MNQ] 09:51 \ud83d\udd34 C=25093.75 EMA=-7.7961",
    "[09:52:01] [MGC] 09:51 \ud83d\udd34 C=5172.90 EMA=-0.8521",
    "[09:52:41] \ud83d\udcca [MGC] \ud83d\udd34 EMA=-0.85 | [MNQ] \ud83d\udd34 EMA=-7.80",
    "[09:53:00] [MNQ] 09:52 \ud83d\udd34 C=25090.75 EMA=-10.9437",
    "[09:53:00] [MGC] 09:52 \ud83d\udd34 C=5172.50 EMA=-1.1065"
  ]
}