{
  "status": "live",
  "asset": "MGC + MNQ + SIL",
  "account_mode": "practice",
  "started_at": "2026-02-25T11:39:26.414651+00:00",
  "updated_at": "2026-02-25T12:22:30.217360+00:00",
  "windows": [
    "[MGC] 23:00-23:30 CC=0.8",
    "[MGC] 01:00-01:30 CC=4.7",
    "[MGC] 02:00-02:30 CC=1.2",
    "[MGC] 00:00-00:30 CC=2.7",
    "[MGC] 14:00-14:30 CC=1.0",
    "[MNQ] 17:00-17:30 CC=6.6",
    "[MNQ] 21:00-21:30 CC=1.3",
    "[MNQ] 16:00-16:30 CC=4.6",
    "[MNQ] 20:30-21:00 CC=9.6",
    "[MNQ] 00:30-01:00 CC=2.3"
  ],
  "balance": 148987.04,
  "start_balance": 148987.04,
  "pnl": 0.0,
  "pnl_pct": 0.0,
  "trades": 0,
  "wins": 0,
  "losses": 0,
  "win_rate": 0,
  "open_orders": 0,
  "open_positions": 0,
  "last_signal": "",
  "cloud_color": "green",
  "ema_diff": 2.3142,
  "terminal": [
    "[12:11:59] [MNQ] \u2192 \ud83d\udccf CC zu klein | CC Size: 0.75 < 1.3",
    "[12:12:24] \ud83d\udcca [MGC] \ud83d\udfe2 EMA=+2.29 | [MNQ] \ud83d\udd34 EMA=-1.23 | [SIL] \ud83d\udfe2 EMA=+0.14",
    "[12:12:59] [MNQ] 12:12 \ud83d\udd34 C=25112.75 EMA=-2.3653",
    "[12:12:59] [MGC] 12:12 \ud83d\udfe2 C=5199.00 EMA=+1.8554",
    "[12:13:01] [SIL] 12:12 \ud83d\udfe2 C=90.39 EMA=+0.1027",
    "[12:13:24] \ud83d\udcca [MGC] \ud83d\udfe2 EMA=+1.86 | [MNQ] \ud83d\udd34 EMA=-2.37 | [SIL] \ud83d\udfe2 EMA=+0.10",
    "[12:13:59] [MNQ] 12:13 \ud83d\udd34 C=25107.25 EMA=-4.5656",
    "[12:14:00] [SIL] 12:13 \ud83d\udfe2 C=90.37 EMA=+0.0738",
    "[12:14:01] [MGC] 12:13 \ud83d\udfe2 C=5199.60 EMA=+1.7318",
    "[12:14:27] \ud83d\udcca [MGC] \ud83d\udfe2 EMA=+1.73 | [MNQ] \ud83d\udd34 EMA=-4.57 | [SIL] \ud83d\udfe2 EMA=+0.07",
    "[12:14:59] [MGC] 12:14 \ud83d\udfe2 C=5199.90 EMA=+1.6902",
    "[12:14:59] [MNQ] 12:14 \ud83d\udd34 C=25112.00 EMA=-4.1386",
    "[12:15:01] [SIL] 12:14 \ud83d\udfe2 C=90.31 EMA=+0.0355",
    "[12:15:25] \ud83d\udcca [MGC] \ud83d\udfe2 EMA=+1.69 | [MNQ] \ud83d\udd34 EMA=-4.14 | [SIL] \ud83d\udfe2 EMA=+0.04",
    "[12:15:59] [MNQ] 12:15 \ud83d\udd34 C=25113.75 EMA=-3.2157",
    "[12:16:01] [MGC] 12:15 \ud83d\udfe2 C=5200.40 EMA=+1.7555",
    "[12:16:28] \ud83d\udcca [MGC] \ud83d\udfe2 EMA=+1.76 | [MNQ] \ud83d\udd34 EMA=-3.22 | [SIL] \ud83d\udfe2 EMA=+0.04",
    "[12:16:59] [MNQ] 12:16 \ud83d\udd34 C=25116.00 EMA=-1.9065",
    "[12:17:00] [MGC] 12:16 \ud83d\udfe2 C=5202.50 EMA=+2.3642",
    "[12:17:27] \ud83d\udcca [MGC] \ud83d\udfe2 EMA=+2.36 | [MNQ] \ud83d\udd34 EMA=-1.91 | [SIL] \ud83d\udfe2 EMA=+0.04",
    "[12:17:59] [MGC] 12:17 \ud83d\udfe2 C=5201.80 EMA=+2.3912",
    "[12:17:59] [MNQ] 12:17 \ud83d\udd34 C=25116.25 EMA=-1.0470",
    "[12:18:29] \ud83d\udcca [MGC] \ud83d\udfe2 EMA=+2.39 | [MNQ] \ud83d\udd34 EMA=-1.05 | [SIL] \ud83d\udfe2 EMA=+0.04",
    "[12:18:59] [MGC] 12:18 \ud83d\udfe2 C=5202.60 EMA=+2.5585",
    "[12:18:59] [MNQ] 12:18 \ud83d\udd34 C=25117.00 EMA=-0.3120",
    "[12:19:28] \ud83d\udcca [MGC] \ud83d\udfe2 EMA=+2.56 | [MNQ] \ud83d\udd34 EMA=-0.31 | [SIL] \ud83d\udfe2 EMA=+0.04",
    "[12:19:59] [MNQ] 12:19 \ud83d\udfe2\u26a1 C=25128.00 EMA=+3.4513",
    "[12:19:59] [MNQ] \u2192 \ud83d\udccf CC zu klein | CC Size: 0.25 < 1.3",
    "[12:19:59] [MGC] 12:19 \ud83d\udfe2 C=5201.60 EMA=+2.2472",
    "[12:20:01] [SIL] 12:19 \ud83d\udd34\u26a1 C=90.25 EMA=-0.0034",
    "[12:20:01] [SIL] \u2192 \ud83d\udccf CC zu klein | CC Size: 0.00 < 0.032",
    "[12:20:31] \ud83d\udcca [MGC] \ud83d\udfe2 EMA=+2.25 | [MNQ] \ud83d\udfe2 EMA=+3.45 | [SIL] \ud83d\udd34 EMA=-0.00",
    "[12:20:59] [MNQ] 12:20 \ud83d\udfe2 C=25139.50 EMA=+8.8675",
    "[12:20:59] [MGC] 12:20 \ud83d\udfe2 C=5203.30 EMA=+2.5106",
    "[12:21:01] [SIL] 12:20 \ud83d\udd34 C=90.27 EMA=-0.0183",
    "[12:21:29] \ud83d\udcca [MGC] \ud83d\udfe2 EMA=+2.51 | [MNQ] \ud83d\udfe2 EMA=+8.87 | [SIL] \ud83d\udd34 EMA=-0.02",
    "[12:21:59] [MNQ] 12:21 \ud83d\udfe2 C=25143.75 EMA=+12.7652",
    "[12:22:00] [MGC] 12:21 \ud83d\udfe2 C=5202.50 EMA=+2.3142",
    "[12:22:01] [SIL] 12:21 \ud83d\udfe2\u26a1 C=90.37 EMA=+0.0048",
    "[12:22:01] [SIL] \u2192 \ud83d\udccf CC zu klein | CC Size: 0.00 < 0.032"
  ]
}